setup.py
baemo/__init__.py
baemo/collection.py
baemo/connection.py
baemo/delimited.py
baemo/entity.py
baemo/exceptions.py
baemo/model.py
baemo/projection.py
baemo/references.py
baemo/sort.py
baemo.egg-info/PKG-INFO
baemo.egg-info/SOURCES.txt
baemo.egg-info/dependency_links.txt
baemo.egg-info/requires.txt
baemo.egg-info/top_level.txt
test/test_collection.py
test/test_connection.py
test/test_delimited.py
test/test_entity.py
test/test_exceptions.py
test/test_model.py
test/test_projection.py
test/test_references.py
test/test_sort.py