Metadata-Version: 1.1
Name: baemo
Version: 0.0.9
Summary: MongoDB ORM / ODM
Home-page: https://github.com/chrisantonellis/baemo
Author: Christopher Antonellis
Author-email: christopher.antonellis@gmail.com
License: MIT
Keywords: mongodb pymongo orm odm relationship reference unit-of-work
Platform: UNKNOWN
Classifier: Development Status :: 3 - Alpha
Classifier: Intended Audience :: Developers
Classifier: License :: OSI Approved :: MIT License
Classifier: Natural Language :: English
Classifier: Programming Language :: Python :: 3
Classifier: Programming Language :: Python :: 3.6
